api_arsenal_iabdullahban/__init__.py
api_arsenal_iabdullahban/api_arsenal.py
api_arsenal_iabdullahban-0.0.2.dist-info/LICENSE
api_arsenal_iabdullahban-0.0.2.dist-info/METADATA
api_arsenal_iabdullahban-0.0.2.dist-info/WHEEL
api_arsenal_iabdullahban-0.0.2.dist-info/top_level.txt
api_arsenal_iabdullahban-0.0.2.dist-info/RECORD
