Metadata-Version: 2.2
Name: api_arsenal_iabdullahban
Version: 0.0.2
Summary: This library was developed to simplify handling HTTP requests, logging responses, and deriving statistics from them. It provides tools for testing and monitoring the performance of endpoints and generating detailed reports on successful and non-successful responses.
Author-email: Abdullah Al-Shehri <iabdullahban@gmail.com>
License: Copyright (c) 2018 The Python Packaging Authority
Classifier: Programming Language :: Python :: 3
Classifier: Operating System :: OS Independent
Requires-Python: >=3.8
License-File: LICENSE
